nextnextping/__init__.py
nextnextping/grammer/__init__.py
nextnextping/grammer/ttl_parser.g4
nextnextping/grammer/ttl_parser.interp
nextnextping/grammer/ttl_parser.tokens
nextnextping/grammer/ttl_parser_lexer.interp
nextnextping/grammer/ttl_parser_lexer.py
nextnextping/grammer/ttl_parser_lexer.tokens
nextnextping/grammer/ttl_parser_listener.py
nextnextping/grammer/ttl_parser_parser.py
nextnextping/grammer/ttl_parser_visitor.py
nextnextping/grammer/ttl_parser_worker.py
nextnextping/grammer/version.py
nextnextping/nextnextping.py
nextnextping/pyttl.py
nextnextping-1.29.1.dist-info/METADATA
nextnextping-1.29.1.dist-info/WHEEL
nextnextping-1.29.1.dist-info/entry_points.txt
nextnextping-1.29.1.dist-info/licenses/LICENSE
nextnextping-1.29.1.dist-info/RECORD
