Metadata-Version: 2.4
Name: nextnextping
Version: 1.29.1
Summary: You can connect via SSH using a language called TTL(Terawaros Tekitou Language), which is similar to teraterm macro, and ping other servers as stepping stones.
License-File: LICENSE
Author: Toshikazu Ando
Author-email: foobar@em.boo.jp
Requires-Python: >=3.12
Classifier: Programming Language :: Python :: 3
Classifier: Programming Language :: Python :: 3.12
Classifier: Programming Language :: Python :: 3.13
Classifier: Programming Language :: Python :: 3.14
Requires-Dist: antlr4-python3-runtime
Requires-Dist: cryptography
Requires-Dist: paramiko
Requires-Dist: pexpect
Requires-Dist: pyserial
Requires-Dist: uptime
